<?xml version="1.0" encoding="UTF-8"?>
<actor vx="0" vy="0" tipo="mira">
	<animaciones>
		<animacion estado="normal" img="mira" sec="0" filas="1" columnas="2" retardo="0" />
		<animacion estado="normal-pj1" img="mira" sec="0" filas="1" columnas="2" retardo="0" />
		<animacion estado="normal-pj2" img="mira" sec="1" filas="1" columnas="2" retardo="0" />
	</animaciones>
	<colisiones>
		<punto estado="normal" x="15" y="15" />
		<punto estado="normal-pj1" x="15" y="15" />
		<punto estado="normal-pj2" x="15" y="15" />
	</colisiones>
</actor>
